nozama/__init__.py
nozama/cloudsearch/__init__.py
nozama/cloudsearch/client/__init__.py
nozama/cloudsearch/client/rest.py
nozama/cloudsearch/data/__init__.py
nozama/cloudsearch/data/db.py
nozama/cloudsearch/data/document.py
nozama/cloudsearch/service/__init__.py
nozama/cloudsearch/service/environ_settings.py
nozama/cloudsearch/service/nozamaviews.py
nozama/cloudsearch/service/restfulhelpers.py
nozama/cloudsearch/service/views.py
nozama/cloudsearch/service/docs/__init__.py
tests/__init__.py
tests/conftest.py
tests/test_backend_searching.py
tests/test_documentops.py
tests/test_querying.py
tests/test_serviceapi.py
nozama_cloudsearch-2.0.4.dist-info/LICENSE
nozama_cloudsearch-2.0.4.dist-info/METADATA
nozama_cloudsearch-2.0.4.dist-info/WHEEL
nozama_cloudsearch-2.0.4.dist-info/entry_points.txt
nozama_cloudsearch-2.0.4.dist-info/top_level.txt
nozama_cloudsearch-2.0.4.dist-info/RECORD
