Metadata-Version: 2.1
Name: nozama-cloudsearch
Version: 2.0.4
Summary: A REST service which emulates Amazon CloudSearch for local testing.
Home-page: https://github.com/oisinmulvihill/nozama-cloudsearch
Author: Oisin Mulvihill
Author-email: oisin.mulvihilli@gmail.com
License: BSD
Platform: UNKNOWN
Classifier: Programming Language :: Python :: 3
Classifier: Intended Audience :: Developers
Classifier: License :: OSI Approved :: BSD License
Classifier: Operating System :: OS Independent
Requires-Dist: pymongo
Requires-Dist: elasticsearch
Requires-Dist: decorator
Requires-Dist: paste
Requires-Dist: formencode
Requires-Dist: pyramid
Requires-Dist: pyramid-jinja2
Requires-Dist: pyramid-beaker
Requires-Dist: waitress
Requires-Dist: requests
